{
  "显示日期": "2026/06/09 13:56",
  "票据类型": "电子银行承兑汇票",
  "出票日期": "2026-05-07",
  "汇票到期日": "2026-11-07",
  "票据状态": "已收票- 已锁定",
  "票据号码": "   5 323301000019 20260507 10075875 9 117000001-133000000",
  "出票人": {
    "全称": "全  称 张家港保税区展翼新能源有限公司",
    "账号": "18801001000009954",
    "开户银行": "江苏苏商银行股份有限公司"
  },
  "收款人": {
    "全称": "全  称 浙江九易能源有限公司",
    "账号": "3310010710120100129448",
    "开户银行": "浙商银行股份有限公司杭州城东支行"
  },
  "票据金额": {
    "币种": "人民币",
    "大写金额": "壹拾陆万元整",
    "小写金额": "160000.00"
  },
  "承兑人": {
    "全称": "江苏苏商银行股份有限公司",
    "开户行行号": "323301000019"
  },
  "出票人承诺": "出票人承诺：本汇票请予以承兑，到期无条件付款",
  "能否转让": "交易合同号 承 兑 信 息 能否转让 可再转让 — 允许分包流转",
  "承兑人承诺": "承兑人承兑：本汇票已经承兑，到期无条件付款",
  "承兑日期": "2026-05-07"
}